NEURON_gpu-8.2.2.dist-info/WHEEL
NEURON_gpu-8.2.2.dist-info/top_level.txt
NEURON_gpu-8.2.2.dist-info/RECORD
NEURON_gpu-8.2.2.dist-info/METADATA
NEURON_gpu-8.2.2.data/scripts/mkthreadsafe
NEURON_gpu-8.2.2.data/scripts/nrngui
NEURON_gpu-8.2.2.data/scripts/nrniv-core
NEURON_gpu-8.2.2.data/scripts/nrnivmodl
NEURON_gpu-8.2.2.data/scripts/modlunit
NEURON_gpu-8.2.2.data/scripts/neurondemo
NEURON_gpu-8.2.2.data/scripts/nrnpyenv.sh
NEURON_gpu-8.2.2.data/scripts/nrniv
NEURON_gpu-8.2.2.data/scripts/nrnivmodl-core
NEURON_gpu-8.2.2.data/scripts/idraw
NEURON_gpu-8.2.2.data/scripts/sortspike
NEURON_gpu.libs/libcudadevice-5901c3a2.so
NEURON_gpu.libs/libnvhpcatm-406400d8.so
NEURON_gpu.libs/libnrniv-36ed8887.so
NEURON_gpu.libs/libnvcpumath-avx2-91375214.so
NEURON_gpu.libs/libcudart-4554289f.so.11.5.117
NEURON_gpu.libs/libnvc-ca879ffd.so
NEURON_gpu.libs/libcudanvhpc-8257c6fc.so
NEURON_gpu.libs/libnvomp-fb1a2b9f.so
NEURON_gpu.libs/libacccuda-43e350a6.so
NEURON_gpu.libs/libaccdevaux-f0c679c6.so
NEURON_gpu.libs/libacchost-c31344de.so
neuron/sections.py
neuron/units.py
neuron/help_data.dat
neuron/doc.py
neuron/hclass3.py
neuron/expect_hocerr.py
neuron/gui.py
neuron/hoc.cpython-310-x86_64-linux-gnu.so
neuron/nonvint_block_supervisor.py
neuron/psection.py
neuron/__init__.py
neuron/coreneuron.py
neuron/gui2/rangevar.py
neuron/gui2/utilities.py
neuron/gui2/plotshape.py
neuron/gui2/config.py
neuron/gui2/__init__.py
neuron/gui2/setup_threejs.py
neuron/tests/test_neuron.py
neuron/tests/_subclass.py
neuron/tests/test_all.py
neuron/tests/__init__.py
neuron/tests/test_vector.py
neuron/tests/test_rxd.py
neuron/crxd/__init__.py
neuron/.data/lib/libcorenrnmech.a
neuron/.data/lib/libinterviews.a
neuron/.data/lib/libcorenrnmpi_mpt.so
neuron/.data/lib/libscopmath.a
neuron/.data/lib/libunidraw.a
neuron/.data/lib/libcorenrnmpi_ompi.so
neuron/.data/lib/libnrnpython3.so
neuron/.data/lib/libcoreneuron.a
neuron/.data/lib/libnrniv.so
neuron/.data/lib/libnrnmpi_mpt.so
neuron/.data/lib/libivx11dynam.so
neuron/.data/lib/librxdmath.so
neuron/.data/lib/libcorenrnmpi_mpich.so
